streamlit_ripples/__init__.py
streamlit_ripples/example.py
streamlit_ripples/frontend/build/asset-manifest.json
streamlit_ripples/frontend/build/bootstrap.min.css
streamlit_ripples/frontend/build/index.html
streamlit_ripples/frontend/build/static/js/main.3460bb83.js
streamlit_ripples/frontend/build/static/js/main.3460bb83.js.LICENSE.txt
streamlit_ripples/frontend/build/static/js/main.3460bb83.js.map
streamlit_ripples-0.0.1.dist-info/LICENSE
streamlit_ripples-0.0.1.dist-info/METADATA
streamlit_ripples-0.0.1.dist-info/WHEEL
streamlit_ripples-0.0.1.dist-info/top_level.txt
streamlit_ripples-0.0.1.dist-info/RECORD
